optional_faker.py
optional_faker-2.1.0.dist-info/LICENSE
optional_faker-2.1.0.dist-info/METADATA
optional_faker-2.1.0.dist-info/WHEEL
optional_faker-2.1.0.dist-info/RECORD
